bnipython/__init__.py
bnipython/lib/bniClient.py
bnipython/lib/api/bniMove.py
bnipython/lib/api/oneGatePayment.py
bnipython/lib/api/rdf.py
bnipython/lib/api/rdl.py
bnipython/lib/api/rdn.py
bnipython/lib/api/snapBI.py
bnipython/lib/net/httpClient.py
bnipython/lib/util/constants.py
bnipython/lib/util/response.py
bnipython/lib/util/utils.py
bnipython-0.8.9.dist-info/LICENSE
bnipython-0.8.9.dist-info/METADATA
bnipython-0.8.9.dist-info/WHEEL
bnipython-0.8.9.dist-info/top_level.txt
bnipython-0.8.9.dist-info/RECORD
