Metadata-Version: 2.1
Name: bnipython
Version: 0.8.9
Summary: Official  BNI API SDK for Python
Home-page: https://github.com/bni-api/bni-python-sdk/
Author: BNI API
Author-email: 
License: MIT
Classifier: Programming Language :: Python
Classifier: Programming Language :: Python :: 3
Classifier: Programming Language :: Python :: 3 :: Only
Classifier: Programming Language :: Python :: 3.5
Classifier: Programming Language :: Python :: 3.6
Classifier: Programming Language :: Python :: 3.7
Classifier: Programming Language :: Python :: 3.8
Classifier: Programming Language :: Python :: 3.9
Classifier: Programming Language :: Python :: 3.10
Classifier: Topic :: Software Development :: Libraries :: Python Modules
Requires-Python: >=3.5
License-File: LICENSE
Requires-Dist: requests >=2.25.0
Requires-Dist: pyOpenSSL >=22.0.0
Requires-Dist: pytz >=2022.2.1
